pytest_moto_fixtures/__init__.py
pytest_moto_fixtures/fixtures.py
pytest_moto_fixtures/py.typed
pytest_moto_fixtures/services/__init__.py
pytest_moto_fixtures/services/eventbridge.py
pytest_moto_fixtures/services/s3.py
pytest_moto_fixtures/services/sns.py
pytest_moto_fixtures/services/sqs.py
pytest_moto_fixtures/utils.py
pytest_moto_fixtures-0.0.1a4.dist-info/METADATA
pytest_moto_fixtures-0.0.1a4.dist-info/WHEEL
pytest_moto_fixtures-0.0.1a4.dist-info/entry_points.txt
pytest_moto_fixtures-0.0.1a4.dist-info/licenses/LICENSE
pytest_moto_fixtures-0.0.1a4.dist-info/RECORD
