Metadata-Version: 2.4
Name: pytest-moto-fixtures
Version: 0.0.1a4
Summary: Fixtures for testing code that interacts with AWS
License-Expression: MIT
License-File: LICENSE
Author: Eduardo Klosowski
Author-email: eduardo_klosowski@yahoo.com
Requires-Python: >=3.10
Classifier: Development Status :: 1 - Planning
Classifier: Environment :: Plugins
Classifier: Framework :: Pytest
Classifier: Intended Audience :: Developers
Classifier: Operating System :: OS Independent
Classifier: Programming Language :: Python :: 3
Classifier: Programming Language :: Python :: 3.10
Classifier: Programming Language :: Python :: 3.11
Classifier: Programming Language :: Python :: 3.12
Classifier: Programming Language :: Python :: 3.13
Classifier: Programming Language :: Python :: 3.14
Classifier: Topic :: Software Development
Classifier: Topic :: Software Development :: Testing
Classifier: Topic :: Software Development :: Testing :: Mocking
Classifier: Typing :: Typed
Provides-Extra: pytest
Requires-Dist: boto3 (>=1.36,<1.41)
Requires-Dist: moto[events,s3,sns,sqs] (>=5.1,<5.2) ; extra == "pytest"
Requires-Dist: pytest (>=8.3,<9.1) ; extra == "pytest"
Project-URL: Documentation, https://pytest-moto-fixtures.readthedocs.io/
Project-URL: Repository, https://github.com/eduardoklosowski/pytest-moto-fixtures.git
Project-URL: Release notes, https://github.com/eduardoklosowski/pytest-moto-fixtures/releases
